dbtbasic/__init__.py
dbtbasic/yaml.py
dbtbasic-0.0.1.dist-info/METADATA
dbtbasic-0.0.1.dist-info/WHEEL
dbtbasic-0.0.1.dist-info/licenses/LICENSE
dbtbasic-0.0.1.dist-info/RECORD
